{
  "total_games": 25,
  "p1_wins": 25,
  "p2_wins": 0,
  "draws": 0,
  "avg_moves": 41.24,
  "avg_time_ms": 133112.88,
  "games": [
    {
      "winner": "Player1",
      "moves": 27,
      "time_ms": 102213
    },
    {
      "winner": "Player1",
      "moves": 23,
      "time_ms": 73780
    },
    {
      "winner": "Player1",
      "moves": 33,
      "time_ms": 85344
    },
    {
      "winner": "Player1",
      "moves": 39,
      "time_ms": 185752
    },
    {
      "winner": "Player1",
      "moves": 35,
      "time_ms": 99994
    },
    {
      "winner": "Player1",
      "moves": 49,
      "time_ms": 131902
    },
    {
      "winner": "Player1",
      "moves": 23,
      "time_ms": 71280
    },
    {
      "winner": "Player1",
      "moves": 57,
      "time_ms": 143926
    },
    {
      "winner": "Player1",
      "moves": 47,
      "time_ms": 167316
    },
    {
      "winner": "Player1",
      "moves": 61,
      "time_ms": 319163
    },
    {
      "winner": "Player1",
      "moves": 45,
      "time_ms": 138325
    },
    {
      "winner": "Player1",
      "moves": 47,
      "time_ms": 278184
    },
    {
      "winner": "Player1",
      "moves": 49,
      "time_ms": 183941
    },
    {
      "winner": "Player1",
      "moves": 53,
      "time_ms": 186636
    },
    {
      "winner": "Player1",
      "moves": 53,
      "time_ms": 92827
    },
    {
      "winner": "Player1",
      "moves": 37,
      "time_ms": 132820
    },
    {
      "winner": "Player1",
      "moves": 51,
      "time_ms": 126357
    },
    {
      "winner": "Player1",
      "moves": 35,
      "time_ms": 92661
    },
    {
      "winner": "Player1",
      "moves": 37,
      "time_ms": 165761
    },
    {
      "winner": "Player1",
      "moves": 51,
      "time_ms": 109719
    },
    {
      "winner": "Player1",
      "moves": 29,
      "time_ms": 50718
    },
    {
      "winner": "Player1",
      "moves": 39,
      "time_ms": 125443
    },
    {
      "winner": "Player1",
      "moves": 25,
      "time_ms": 54458
    },
    {
      "winner": "Player1",
      "moves": 53,
      "time_ms": 137062
    },
    {
      "winner": "Player1",
      "moves": 33,
      "time_ms": 72240
    }
  ]
}